opendash/__about__.py
opendash/__init__.py
opendash/__main__.py
opendash/bundle.py
opendash/config.py
opendash/assets/assets_bundler.py
opendash/assets/open_dash_output.py
opendash/assets/server/Dockerfile.lambda
opendash/assets/server/index.py
opendash/assets/warmer/index.py
opendash/assets/warmer/requirements.txt
open_dash-0.1.0.dist-info/METADATA
open_dash-0.1.0.dist-info/WHEEL
open_dash-0.1.0.dist-info/entry_points.txt
open_dash-0.1.0.dist-info/licenses/LICENSE
open_dash-0.1.0.dist-info/RECORD
