Metadata-Version: 2.4
Name: open-dash
Version: 0.1.0
Summary: Open Dash packages Plotly dash applications for deployment to AWS S3 and Lambda. Developed by Zonké.
Project-URL: Homepage, https://zonke.dev
Project-URL: Documentation, https://github.com/zonke-inc/open-dash#readme
Project-URL: Issues, https://github.com/zonke-inc/open-dash/issues
Project-URL: Source, https://github.com/zonke-inc/open-dash
Author-email: "Zonké, Inc." <support@zonke.dev>
License-Expression: MIT
License-File: LICENSE
Keywords: dash,deployment,serverless,zonke
Classifier: Development Status :: 4 - Beta
Classifier: Environment :: Web Environment
Classifier: Framework :: Dash
Classifier: Framework :: Flask
Classifier: Intended Audience :: Developers
Classifier: Intended Audience :: Science/Research
Classifier: License :: OSI Approved :: MIT License
Classifier: Programming Language :: Python
Classifier: Programming Language :: Python :: 3.8
Classifier: Programming Language :: Python :: 3.9
Classifier: Programming Language :: Python :: 3.10
Classifier: Programming Language :: Python :: 3.11
Classifier: Programming Language :: Python :: 3.12
Classifier: Programming Language :: Python :: Implementation :: CPython
Classifier: Programming Language :: Python :: Implementation :: PyPy
Classifier: Topic :: Software Development :: Build Tools
Requires-Python: >=3.8
